netort/__init__.py
netort/data_processing.py
netort/logging_and_signals.py
netort/process.py
netort/resource.py
netort/usb_devices.py
netort/validated_config.py
netort/data_manager/__init__.py
netort/data_manager/manager.py
netort/data_manager/router.py
netort/data_manager/clients/__init__.py
netort/data_manager/clients/local.py
netort/data_manager/clients/luna.py
netort/data_manager/clients/lunapark_volta.py
netort/data_manager/common/__init__.py
netort/data_manager/common/interfaces.py
netort/data_manager/common/util.py
netort/data_manager/metrics/__init__.py
netort/data_manager/metrics/aggregate.py
netort/data_manager/metrics/distribution.py
netort/data_manager/metrics/event.py
netort/data_manager/metrics/histogram.py
netort/data_manager/metrics/metric.py
netort-0.2.4.dist-info/METADATA
netort-0.2.4.dist-info/RECORD
netort-0.2.4.dist-info/WHEEL
netort-0.2.4.dist-info/top_level.txt
