Metadata-Version: 2.1
Name: netort
Version: 0.2.4
Summary: common library for yandex-load org
Home-page: http://github.com/yandex-load/netort
Maintainer: Timur Torubarov (load testing)
Maintainer-email: netort@yandex-team.ru
License: MPLv2
Platform: UNKNOWN
Classifier: Development Status :: 5 - Production/Stable
Classifier: Environment :: Console
Classifier: Environment :: Web Environment
Classifier: Intended Audience :: End Users/Desktop
Classifier: Intended Audience :: Developers
Classifier: Intended Audience :: System Administrators
Classifier: License :: OSI Approved :: GNU Lesser General Public License v2 or later (LGPLv2+)
Classifier: Operating System :: POSIX
Classifier: Topic :: Software Development :: Quality Assurance
Classifier: Topic :: Software Development :: Testing
Classifier: Topic :: Software Development :: Testing :: Traffic Generation
Classifier: Programming Language :: Python :: 2
Classifier: Programming Language :: Python :: 3
Requires-Dist: pyserial
Requires-Dist: requests
Requires-Dist: cerberus
